dump_github/__init__.py
dump_github/lib.py
dump_github/main.py
dump_github/mylib.py
dump_github-0.1.7.dist-info/LICENSE
dump_github-0.1.7.dist-info/METADATA
dump_github-0.1.7.dist-info/WHEEL
dump_github-0.1.7.dist-info/entry_points.txt
dump_github-0.1.7.dist-info/top_level.txt
dump_github-0.1.7.dist-info/RECORD
