Metadata-Version: 2.1
Name: dump-github
Version: 0.1.7
Summary: This tool can be used to back up users' GitHub repositories in case they need them later.
Home-page: https://github.com/core2002/dump_github
Author: core2002
Author-email: core2002@aliyun.com
License: MIT
Classifier: Programming Language :: Python :: 3
Classifier: License :: OSI Approved :: MIT License
Classifier: Operating System :: OS Independent
License-File: LICENSE
Requires-Dist: argparse
Requires-Dist: requests
